odoo_env/__init__.py
odoo_env/client.py
odoo_env/command.py
odoo_env/config.py
odoo_env/constants.py
odoo_env/create_database.py
odoo_env/deploy_keys.py
odoo_env/images.py
odoo_env/messages.py
odoo_env/odoo_conf.py
odoo_env/odooenv.py
odoo_env/oe.py
odoo_env/options.py
odoo_env/repos.py
odoo_env/sd.py
odoo_env/test_oe.py
odoo_env/data/__manifest__.py
odoo_env/data/nginx.conf
odoo_env/data/nginx.crt
odoo_env/data/nginx.key
odoo_env/data/nginx_ssh.conf
odoo_env/doc/restore.hlp
odoo_env-0.16.5.dist-info/METADATA
odoo_env-0.16.5.dist-info/WHEEL
odoo_env-0.16.5.dist-info/entry_points.txt
odoo_env-0.16.5.dist-info/licenses/LICENSE.txt
odoo_env-0.16.5.dist-info/RECORD
