Metadata-Version: 2.4
Name: odoo-env
Version: 0.16.5
Summary: A Dockerized environment for Odoo
Project-URL: Homepage, https://jobiols.github.io/odoo-env/
Project-URL: Bug Tracker, https://github.com/jobiols/odoo-env/issues
Author-email: Jorge Obiols <jorge.obiols@gmail.com>
License-File: LICENSE.txt
Classifier: Development Status :: 5 - Production/Stable
Classifier: Intended Audience :: Developers
Classifier: License :: OSI Approved :: MIT License
Classifier: Operating System :: POSIX :: Linux
Classifier: Programming Language :: Python :: 3.10
Classifier: Programming Language :: Python :: 3.11
Classifier: Programming Language :: Python :: 3.12
Classifier: Programming Language :: Python :: 3.13
Classifier: Topic :: Software Development :: Testing :: Unit
Classifier: Topic :: System :: Software Distribution
Requires-Python: >=3.9
Requires-Dist: pyyaml>=6.0.2
Requires-Dist: tornado>=6.4.2
